odoo/addons/hr_contract_type/README.rst
odoo/addons/hr_contract_type/__init__.py
odoo/addons/hr_contract_type/__manifest__.py
odoo/addons/hr_contract_type/hooks.py
odoo/addons/hr_contract_type/i18n/es.po
odoo/addons/hr_contract_type/i18n/es_PA.po
odoo/addons/hr_contract_type/i18n/hr_contract_type.pot
odoo/addons/hr_contract_type/i18n/it.po
odoo/addons/hr_contract_type/i18n/pt_BR.po
odoo/addons/hr_contract_type/models/__init__.py
odoo/addons/hr_contract_type/models/hr_contract.py
odoo/addons/hr_contract_type/models/hr_contract_type.py
odoo/addons/hr_contract_type/readme/CONTRIBUTORS.rst
odoo/addons/hr_contract_type/readme/DESCRIPTION.rst
odoo/addons/hr_contract_type/readme/ROADMAP.rst
odoo/addons/hr_contract_type/security/ir.model.access.csv
odoo/addons/hr_contract_type/static/description/icon.png
odoo/addons/hr_contract_type/static/description/index.html
odoo/addons/hr_contract_type/views/hr_contract.xml
odoo/addons/hr_contract_type/views/hr_contract_type.xml
odoo_addon_hr_contract_type-15.0.1.0.0.2.dist-info/METADATA
odoo_addon_hr_contract_type-15.0.1.0.0.2.dist-info/WHEEL
odoo_addon_hr_contract_type-15.0.1.0.0.2.dist-info/top_level.txt
odoo_addon_hr_contract_type-15.0.1.0.0.2.dist-info/RECORD
